{
  "ok": true,
  "frames_root": "/Users/phoenixicarus/Documents/WorkSpace/Phoenix-Pet/hatch-runs/tuxie-actions/frames",
  "errors": [],
  "warnings": [],
  "rows": [
    {
      "state": "idle",
      "expected_frames": 6,
      "actual_frames": 6,
      "extraction_method": "components",
      "ok": true,
      "errors": [],
      "warnings": [],
      "frames": [
        {
          "index": 0,
          "file": "/Users/phoenixicarus/Documents/WorkSpace/Phoenix-Pet/hatch-runs/tuxie-actions/frames/idle/00.png",
          "width": 192,
          "height": 208,
          "nontransparent_pixels": 20579,
          "bbox": [
            5,
            19,
            187,
            189
          ],
          "edge_pixels": 0,
          "chroma_adjacent_pixels": 153
        },
        {
          "index": 1,
          "file": "/Users/phoenixicarus/Documents/WorkSpace/Phoenix-Pet/hatch-runs/tuxie-actions/frames/idle/01.png",
          "width": 192,
          "height": 208,
          "nontransparent_pixels": 20742,
          "bbox": [
            5,
            18,
            187,
            189
          ],
          "edge_pixels": 0,
          "chroma_adjacent_pixels": 146
        },
        {
          "index": 2,
          "file": "/Users/phoenixicarus/Documents/WorkSpace/Phoenix-Pet/hatch-runs/tuxie-actions/frames/idle/02.png",
          "width": 192,
          "height": 208,
          "nontransparent_pixels": 20596,
          "bbox": [
            5,
            19,
            187,
            189
          ],
          "edge_pixels": 0,
          "chroma_adjacent_pixels": 124
        },
        {
          "index": 3,
          "file": "/Users/phoenixicarus/Documents/WorkSpace/Phoenix-Pet/hatch-runs/tuxie-actions/frames/idle/03.png",
          "width": 192,
          "height": 208,
          "nontransparent_pixels": 20858,
          "bbox": [
            5,
            18,
            187,
            190
          ],
          "edge_pixels": 0,
          "chroma_adjacent_pixels": 122
        },
        {
          "index": 4,
          "file": "/Users/phoenixicarus/Documents/WorkSpace/Phoenix-Pet/hatch-runs/tuxie-actions/frames/idle/04.png",
          "width": 192,
          "height": 208,
          "nontransparent_pixels": 21999,
          "bbox": [
            5,
            8,
            187,
            200
          ],
          "edge_pixels": 0,
          "chroma_adjacent_pixels": 139
        },
        {
          "index": 5,
          "file": "/Users/phoenixicarus/Documents/WorkSpace/Phoenix-Pet/hatch-runs/tuxie-actions/frames/idle/05.png",
          "width": 192,
          "height": 208,
          "nontransparent_pixels": 23987,
          "bbox": [
            5,
            11,
            187,
            197
          ],
          "edge_pixels": 0,
          "chroma_adjacent_pixels": 155
        }
      ]
    },
    {
      "state": "running-right",
      "expected_frames": 8,
      "actual_frames": 8,
      "extraction_method": "components",
      "ok": true,
      "errors": [],
      "warnings": [],
      "frames": [
        {
          "index": 0,
          "file": "/Users/phoenixicarus/Documents/WorkSpace/Phoenix-Pet/hatch-runs/tuxie-actions/frames/running-right/00.png",
          "width": 192,
          "height": 208,
          "nontransparent_pixels": 18408,
          "bbox": [
            5,
            37,
            187,
            171
          ],
          "edge_pixels": 0,
          "chroma_adjacent_pixels": 256
        },
        {
          "index": 1,
          "file": "/Users/phoenixicarus/Documents/WorkSpace/Phoenix-Pet/hatch-runs/tuxie-actions/frames/running-right/01.png",
          "width": 192,
          "height": 208,
          "nontransparent_pixels": 17421,
          "bbox": [
            5,
            40,
            187,
            167
          ],
          "edge_pixels": 0,
          "chroma_adjacent_pixels": 283
        },
        {
          "index": 2,
          "file": "/Users/phoenixicarus/Documents/WorkSpace/Phoenix-Pet/hatch-runs/tuxie-actions/frames/running-right/02.png",
          "width": 192,
          "height": 208,
          "nontransparent_pixels": 16249,
          "bbox": [
            5,
            39,
            187,
            168
          ],
          "edge_pixels": 0,
          "chroma_adjacent_pixels": 208
        },
        {
          "index": 3,
          "file": "/Users/phoenixicarus/Documents/WorkSpace/Phoenix-Pet/hatch-runs/tuxie-actions/frames/running-right/03.png",
          "width": 192,
          "height": 208,
          "nontransparent_pixels": 21269,
          "bbox": [
            5,
            22,
            187,
            186
          ],
          "edge_pixels": 0,
          "chroma_adjacent_pixels": 281
        },
        {
          "index": 4,
          "file": "/Users/phoenixicarus/Documents/WorkSpace/Phoenix-Pet/hatch-runs/tuxie-actions/frames/running-right/04.png",
          "width": 192,
          "height": 208,
          "nontransparent_pixels": 16074,
          "bbox": [
            5,
            42,
            187,
            165
          ],
          "edge_pixels": 0,
          "chroma_adjacent_pixels": 271
        },
        {
          "index": 5,
          "file": "/Users/phoenixicarus/Documents/WorkSpace/Phoenix-Pet/hatch-runs/tuxie-actions/frames/running-right/05.png",
          "width": 192,
          "height": 208,
          "nontransparent_pixels": 17574,
          "bbox": [
            5,
            20,
            187,
            187
          ],
          "edge_pixels": 0,
          "chroma_adjacent_pixels": 291
        },
        {
          "index": 6,
          "file": "/Users/phoenixicarus/Documents/WorkSpace/Phoenix-Pet/hatch-runs/tuxie-actions/frames/running-right/06.png",
          "width": 192,
          "height": 208,
          "nontransparent_pixels": 21611,
          "bbox": [
            5,
            20,
            187,
            187
          ],
          "edge_pixels": 0,
          "chroma_adjacent_pixels": 283
        },
        {
          "index": 7,
          "file": "/Users/phoenixicarus/Documents/WorkSpace/Phoenix-Pet/hatch-runs/tuxie-actions/frames/running-right/07.png",
          "width": 192,
          "height": 208,
          "nontransparent_pixels": 21406,
          "bbox": [
            5,
            26,
            187,
            182
          ],
          "edge_pixels": 0,
          "chroma_adjacent_pixels": 303
        }
      ]
    },
    {
      "state": "running-left",
      "expected_frames": 8,
      "actual_frames": 8,
      "extraction_method": "components",
      "ok": true,
      "errors": [],
      "warnings": [],
      "frames": [
        {
          "index": 0,
          "file": "/Users/phoenixicarus/Documents/WorkSpace/Phoenix-Pet/hatch-runs/tuxie-actions/frames/running-left/00.png",
          "width": 192,
          "height": 208,
          "nontransparent_pixels": 21406,
          "bbox": [
            5,
            26,
            187,
            182
          ],
          "edge_pixels": 0,
          "chroma_adjacent_pixels": 303
        },
        {
          "index": 1,
          "file": "/Users/phoenixicarus/Documents/WorkSpace/Phoenix-Pet/hatch-runs/tuxie-actions/frames/running-left/01.png",
          "width": 192,
          "height": 208,
          "nontransparent_pixels": 21611,
          "bbox": [
            5,
            20,
            187,
            187
          ],
          "edge_pixels": 0,
          "chroma_adjacent_pixels": 283
        },
        {
          "index": 2,
          "file": "/Users/phoenixicarus/Documents/WorkSpace/Phoenix-Pet/hatch-runs/tuxie-actions/frames/running-left/02.png",
          "width": 192,
          "height": 208,
          "nontransparent_pixels": 17574,
          "bbox": [
            5,
            20,
            187,
            187
          ],
          "edge_pixels": 0,
          "chroma_adjacent_pixels": 291
        },
        {
          "index": 3,
          "file": "/Users/phoenixicarus/Documents/WorkSpace/Phoenix-Pet/hatch-runs/tuxie-actions/frames/running-left/03.png",
          "width": 192,
          "height": 208,
          "nontransparent_pixels": 16074,
          "bbox": [
            5,
            42,
            187,
            165
          ],
          "edge_pixels": 0,
          "chroma_adjacent_pixels": 271
        },
        {
          "index": 4,
          "file": "/Users/phoenixicarus/Documents/WorkSpace/Phoenix-Pet/hatch-runs/tuxie-actions/frames/running-left/04.png",
          "width": 192,
          "height": 208,
          "nontransparent_pixels": 21269,
          "bbox": [
            5,
            22,
            187,
            186
          ],
          "edge_pixels": 0,
          "chroma_adjacent_pixels": 281
        },
        {
          "index": 5,
          "file": "/Users/phoenixicarus/Documents/WorkSpace/Phoenix-Pet/hatch-runs/tuxie-actions/frames/running-left/05.png",
          "width": 192,
          "height": 208,
          "nontransparent_pixels": 16249,
          "bbox": [
            5,
            39,
            187,
            168
          ],
          "edge_pixels": 0,
          "chroma_adjacent_pixels": 208
        },
        {
          "index": 6,
          "file": "/Users/phoenixicarus/Documents/WorkSpace/Phoenix-Pet/hatch-runs/tuxie-actions/frames/running-left/06.png",
          "width": 192,
          "height": 208,
          "nontransparent_pixels": 17421,
          "bbox": [
            5,
            40,
            187,
            167
          ],
          "edge_pixels": 0,
          "chroma_adjacent_pixels": 283
        },
        {
          "index": 7,
          "file": "/Users/phoenixicarus/Documents/WorkSpace/Phoenix-Pet/hatch-runs/tuxie-actions/frames/running-left/07.png",
          "width": 192,
          "height": 208,
          "nontransparent_pixels": 18408,
          "bbox": [
            5,
            37,
            187,
            171
          ],
          "edge_pixels": 0,
          "chroma_adjacent_pixels": 256
        }
      ]
    },
    {
      "state": "waving",
      "expected_frames": 4,
      "actual_frames": 4,
      "extraction_method": "components",
      "ok": true,
      "errors": [],
      "warnings": [],
      "frames": [
        {
          "index": 0,
          "file": "/Users/phoenixicarus/Documents/WorkSpace/Phoenix-Pet/hatch-runs/tuxie-actions/frames/waving/00.png",
          "width": 192,
          "height": 208,
          "nontransparent_pixels": 12931,
          "bbox": [
            5,
            36,
            187,
            172
          ],
          "edge_pixels": 0,
          "chroma_adjacent_pixels": 94
        },
        {
          "index": 1,
          "file": "/Users/phoenixicarus/Documents/WorkSpace/Phoenix-Pet/hatch-runs/tuxie-actions/frames/waving/01.png",
          "width": 192,
          "height": 208,
          "nontransparent_pixels": 15071,
          "bbox": [
            5,
            23,
            187,
            185
          ],
          "edge_pixels": 0,
          "chroma_adjacent_pixels": 94
        },
        {
          "index": 2,
          "file": "/Users/phoenixicarus/Documents/WorkSpace/Phoenix-Pet/hatch-runs/tuxie-actions/frames/waving/02.png",
          "width": 192,
          "height": 208,
          "nontransparent_pixels": 16709,
          "bbox": [
            5,
            24,
            187,
            183
          ],
          "edge_pixels": 0,
          "chroma_adjacent_pixels": 135
        },
        {
          "index": 3,
          "file": "/Users/phoenixicarus/Documents/WorkSpace/Phoenix-Pet/hatch-runs/tuxie-actions/frames/waving/03.png",
          "width": 192,
          "height": 208,
          "nontransparent_pixels": 13082,
          "bbox": [
            5,
            34,
            187,
            173
          ],
          "edge_pixels": 0,
          "chroma_adjacent_pixels": 104
        }
      ]
    },
    {
      "state": "jumping",
      "expected_frames": 5,
      "actual_frames": 5,
      "extraction_method": "components",
      "ok": true,
      "errors": [],
      "warnings": [],
      "frames": [
        {
          "index": 0,
          "file": "/Users/phoenixicarus/Documents/WorkSpace/Phoenix-Pet/hatch-runs/tuxie-actions/frames/jumping/00.png",
          "width": 192,
          "height": 208,
          "nontransparent_pixels": 17711,
          "bbox": [
            5,
            32,
            187,
            175
          ],
          "edge_pixels": 0,
          "chroma_adjacent_pixels": 115
        },
        {
          "index": 1,
          "file": "/Users/phoenixicarus/Documents/WorkSpace/Phoenix-Pet/hatch-runs/tuxie-actions/frames/jumping/01.png",
          "width": 192,
          "height": 208,
          "nontransparent_pixels": 17670,
          "bbox": [
            5,
            32,
            187,
            175
          ],
          "edge_pixels": 0,
          "chroma_adjacent_pixels": 143
        },
        {
          "index": 2,
          "file": "/Users/phoenixicarus/Documents/WorkSpace/Phoenix-Pet/hatch-runs/tuxie-actions/frames/jumping/02.png",
          "width": 192,
          "height": 208,
          "nontransparent_pixels": 17076,
          "bbox": [
            5,
            43,
            187,
            164
          ],
          "edge_pixels": 0,
          "chroma_adjacent_pixels": 114
        },
        {
          "index": 3,
          "file": "/Users/phoenixicarus/Documents/WorkSpace/Phoenix-Pet/hatch-runs/tuxie-actions/frames/jumping/03.png",
          "width": 192,
          "height": 208,
          "nontransparent_pixels": 16319,
          "bbox": [
            5,
            41,
            187,
            167
          ],
          "edge_pixels": 0,
          "chroma_adjacent_pixels": 87
        },
        {
          "index": 4,
          "file": "/Users/phoenixicarus/Documents/WorkSpace/Phoenix-Pet/hatch-runs/tuxie-actions/frames/jumping/04.png",
          "width": 192,
          "height": 208,
          "nontransparent_pixels": 23476,
          "bbox": [
            5,
            16,
            187,
            192
          ],
          "edge_pixels": 0,
          "chroma_adjacent_pixels": 263
        }
      ]
    },
    {
      "state": "failed",
      "expected_frames": 8,
      "actual_frames": 8,
      "extraction_method": "components",
      "ok": true,
      "errors": [],
      "warnings": [],
      "frames": [
        {
          "index": 0,
          "file": "/Users/phoenixicarus/Documents/WorkSpace/Phoenix-Pet/hatch-runs/tuxie-actions/frames/failed/00.png",
          "width": 192,
          "height": 208,
          "nontransparent_pixels": 20654,
          "bbox": [
            5,
            36,
            187,
            171
          ],
          "edge_pixels": 0,
          "chroma_adjacent_pixels": 233
        },
        {
          "index": 1,
          "file": "/Users/phoenixicarus/Documents/WorkSpace/Phoenix-Pet/hatch-runs/tuxie-actions/frames/failed/01.png",
          "width": 192,
          "height": 208,
          "nontransparent_pixels": 20412,
          "bbox": [
            5,
            37,
            187,
            171
          ],
          "edge_pixels": 0,
          "chroma_adjacent_pixels": 273
        },
        {
          "index": 2,
          "file": "/Users/phoenixicarus/Documents/WorkSpace/Phoenix-Pet/hatch-runs/tuxie-actions/frames/failed/02.png",
          "width": 192,
          "height": 208,
          "nontransparent_pixels": 22158,
          "bbox": [
            5,
            31,
            187,
            177
          ],
          "edge_pixels": 0,
          "chroma_adjacent_pixels": 175
        },
        {
          "index": 3,
          "file": "/Users/phoenixicarus/Documents/WorkSpace/Phoenix-Pet/hatch-runs/tuxie-actions/frames/failed/03.png",
          "width": 192,
          "height": 208,
          "nontransparent_pixels": 21623,
          "bbox": [
            5,
            35,
            187,
            173
          ],
          "edge_pixels": 0,
          "chroma_adjacent_pixels": 130
        },
        {
          "index": 4,
          "file": "/Users/phoenixicarus/Documents/WorkSpace/Phoenix-Pet/hatch-runs/tuxie-actions/frames/failed/04.png",
          "width": 192,
          "height": 208,
          "nontransparent_pixels": 21486,
          "bbox": [
            5,
            35,
            187,
            173
          ],
          "edge_pixels": 0,
          "chroma_adjacent_pixels": 225
        },
        {
          "index": 5,
          "file": "/Users/phoenixicarus/Documents/WorkSpace/Phoenix-Pet/hatch-runs/tuxie-actions/frames/failed/05.png",
          "width": 192,
          "height": 208,
          "nontransparent_pixels": 20928,
          "bbox": [
            5,
            37,
            187,
            171
          ],
          "edge_pixels": 0,
          "chroma_adjacent_pixels": 198
        },
        {
          "index": 6,
          "file": "/Users/phoenixicarus/Documents/WorkSpace/Phoenix-Pet/hatch-runs/tuxie-actions/frames/failed/06.png",
          "width": 192,
          "height": 208,
          "nontransparent_pixels": 21482,
          "bbox": [
            5,
            34,
            187,
            174
          ],
          "edge_pixels": 0,
          "chroma_adjacent_pixels": 211
        },
        {
          "index": 7,
          "file": "/Users/phoenixicarus/Documents/WorkSpace/Phoenix-Pet/hatch-runs/tuxie-actions/frames/failed/07.png",
          "width": 192,
          "height": 208,
          "nontransparent_pixels": 20801,
          "bbox": [
            5,
            37,
            187,
            171
          ],
          "edge_pixels": 0,
          "chroma_adjacent_pixels": 207
        }
      ]
    },
    {
      "state": "waiting",
      "expected_frames": 6,
      "actual_frames": 6,
      "extraction_method": "components",
      "ok": true,
      "errors": [],
      "warnings": [],
      "frames": [
        {
          "index": 0,
          "file": "/Users/phoenixicarus/Documents/WorkSpace/Phoenix-Pet/hatch-runs/tuxie-actions/frames/waiting/00.png",
          "width": 192,
          "height": 208,
          "nontransparent_pixels": 17486,
          "bbox": [
            5,
            34,
            187,
            173
          ],
          "edge_pixels": 0,
          "chroma_adjacent_pixels": 155
        },
        {
          "index": 1,
          "file": "/Users/phoenixicarus/Documents/WorkSpace/Phoenix-Pet/hatch-runs/tuxie-actions/frames/waiting/01.png",
          "width": 192,
          "height": 208,
          "nontransparent_pixels": 17381,
          "bbox": [
            5,
            43,
            187,
            164
          ],
          "edge_pixels": 0,
          "chroma_adjacent_pixels": 215
        },
        {
          "index": 2,
          "file": "/Users/phoenixicarus/Documents/WorkSpace/Phoenix-Pet/hatch-runs/tuxie-actions/frames/waiting/02.png",
          "width": 192,
          "height": 208,
          "nontransparent_pixels": 18185,
          "bbox": [
            5,
            37,
            187,
            170
          ],
          "edge_pixels": 0,
          "chroma_adjacent_pixels": 209
        },
        {
          "index": 3,
          "file": "/Users/phoenixicarus/Documents/WorkSpace/Phoenix-Pet/hatch-runs/tuxie-actions/frames/waiting/03.png",
          "width": 192,
          "height": 208,
          "nontransparent_pixels": 17707,
          "bbox": [
            5,
            39,
            187,
            169
          ],
          "edge_pixels": 0,
          "chroma_adjacent_pixels": 178
        },
        {
          "index": 4,
          "file": "/Users/phoenixicarus/Documents/WorkSpace/Phoenix-Pet/hatch-runs/tuxie-actions/frames/waiting/04.png",
          "width": 192,
          "height": 208,
          "nontransparent_pixels": 17787,
          "bbox": [
            5,
            35,
            187,
            172
          ],
          "edge_pixels": 0,
          "chroma_adjacent_pixels": 180
        },
        {
          "index": 5,
          "file": "/Users/phoenixicarus/Documents/WorkSpace/Phoenix-Pet/hatch-runs/tuxie-actions/frames/waiting/05.png",
          "width": 192,
          "height": 208,
          "nontransparent_pixels": 18263,
          "bbox": [
            5,
            31,
            187,
            176
          ],
          "edge_pixels": 0,
          "chroma_adjacent_pixels": 183
        }
      ]
    },
    {
      "state": "running",
      "expected_frames": 6,
      "actual_frames": 6,
      "extraction_method": "components",
      "ok": true,
      "errors": [],
      "warnings": [],
      "frames": [
        {
          "index": 0,
          "file": "/Users/phoenixicarus/Documents/WorkSpace/Phoenix-Pet/hatch-runs/tuxie-actions/frames/running/00.png",
          "width": 192,
          "height": 208,
          "nontransparent_pixels": 15512,
          "bbox": [
            5,
            40,
            187,
            167
          ],
          "edge_pixels": 0,
          "chroma_adjacent_pixels": 148
        },
        {
          "index": 1,
          "file": "/Users/phoenixicarus/Documents/WorkSpace/Phoenix-Pet/hatch-runs/tuxie-actions/frames/running/01.png",
          "width": 192,
          "height": 208,
          "nontransparent_pixels": 16351,
          "bbox": [
            5,
            32,
            187,
            176
          ],
          "edge_pixels": 0,
          "chroma_adjacent_pixels": 190
        },
        {
          "index": 2,
          "file": "/Users/phoenixicarus/Documents/WorkSpace/Phoenix-Pet/hatch-runs/tuxie-actions/frames/running/02.png",
          "width": 192,
          "height": 208,
          "nontransparent_pixels": 16052,
          "bbox": [
            5,
            33,
            187,
            174
          ],
          "edge_pixels": 0,
          "chroma_adjacent_pixels": 173
        },
        {
          "index": 3,
          "file": "/Users/phoenixicarus/Documents/WorkSpace/Phoenix-Pet/hatch-runs/tuxie-actions/frames/running/03.png",
          "width": 192,
          "height": 208,
          "nontransparent_pixels": 16056,
          "bbox": [
            5,
            35,
            187,
            173
          ],
          "edge_pixels": 0,
          "chroma_adjacent_pixels": 163
        },
        {
          "index": 4,
          "file": "/Users/phoenixicarus/Documents/WorkSpace/Phoenix-Pet/hatch-runs/tuxie-actions/frames/running/04.png",
          "width": 192,
          "height": 208,
          "nontransparent_pixels": 16639,
          "bbox": [
            5,
            32,
            187,
            175
          ],
          "edge_pixels": 0,
          "chroma_adjacent_pixels": 144
        },
        {
          "index": 5,
          "file": "/Users/phoenixicarus/Documents/WorkSpace/Phoenix-Pet/hatch-runs/tuxie-actions/frames/running/05.png",
          "width": 192,
          "height": 208,
          "nontransparent_pixels": 17403,
          "bbox": [
            5,
            29,
            187,
            178
          ],
          "edge_pixels": 0,
          "chroma_adjacent_pixels": 167
        }
      ]
    },
    {
      "state": "review",
      "expected_frames": 6,
      "actual_frames": 6,
      "extraction_method": "components",
      "ok": true,
      "errors": [],
      "warnings": [],
      "frames": [
        {
          "index": 0,
          "file": "/Users/phoenixicarus/Documents/WorkSpace/Phoenix-Pet/hatch-runs/tuxie-actions/frames/review/00.png",
          "width": 192,
          "height": 208,
          "nontransparent_pixels": 24563,
          "bbox": [
            12,
            5,
            179,
            203
          ],
          "edge_pixels": 0,
          "chroma_adjacent_pixels": 102
        },
        {
          "index": 1,
          "file": "/Users/phoenixicarus/Documents/WorkSpace/Phoenix-Pet/hatch-runs/tuxie-actions/frames/review/01.png",
          "width": 192,
          "height": 208,
          "nontransparent_pixels": 22421,
          "bbox": [
            13,
            5,
            178,
            203
          ],
          "edge_pixels": 0,
          "chroma_adjacent_pixels": 87
        },
        {
          "index": 2,
          "file": "/Users/phoenixicarus/Documents/WorkSpace/Phoenix-Pet/hatch-runs/tuxie-actions/frames/review/02.png",
          "width": 192,
          "height": 208,
          "nontransparent_pixels": 24262,
          "bbox": [
            22,
            5,
            170,
            203
          ],
          "edge_pixels": 0,
          "chroma_adjacent_pixels": 115
        },
        {
          "index": 3,
          "file": "/Users/phoenixicarus/Documents/WorkSpace/Phoenix-Pet/hatch-runs/tuxie-actions/frames/review/03.png",
          "width": 192,
          "height": 208,
          "nontransparent_pixels": 22355,
          "bbox": [
            15,
            5,
            177,
            203
          ],
          "edge_pixels": 0,
          "chroma_adjacent_pixels": 122
        },
        {
          "index": 4,
          "file": "/Users/phoenixicarus/Documents/WorkSpace/Phoenix-Pet/hatch-runs/tuxie-actions/frames/review/04.png",
          "width": 192,
          "height": 208,
          "nontransparent_pixels": 24203,
          "bbox": [
            14,
            5,
            177,
            203
          ],
          "edge_pixels": 0,
          "chroma_adjacent_pixels": 117
        },
        {
          "index": 5,
          "file": "/Users/phoenixicarus/Documents/WorkSpace/Phoenix-Pet/hatch-runs/tuxie-actions/frames/review/05.png",
          "width": 192,
          "height": 208,
          "nontransparent_pixels": 26068,
          "bbox": [
            11,
            5,
            181,
            203
          ],
          "edge_pixels": 0,
          "chroma_adjacent_pixels": 142
        }
      ]
    }
  ]
}
